{"name":"Manager Simulator","intents":[{"intent":"Project","examples":[{"text":"What's my project?"},{"text":"what projects"},{"text":"what to do?"},{"text":"What Project are we working on?"}],"description":"ManagerEnquiresAboutTheProject"},{"intent":"Billys_work","examples":[{"text":"what work are you doing billy?"},{"text":"What  is billy doing ?"},{"text":"What are you working on billy?"}],"description":"work done by billy"},{"intent":"MyEmployees","examples":[{"text":"who are my employees?"},{"text":"who are in my team?"},{"text":"what's my team?"},{"text":"who are in  my team?"}],"description":"ManagerWantsToKnowHisEmployees"},{"intent":"Daily_report_9_4","examples":[{"text":"what's the status on 9/4?"},{"text":"what is the status on 4th?"},{"text":"today is 9/4. what is today's status?"}],"description":"report on 9/4"},{"intent":"Task_to_billy","examples":[{"text":"work on the boss billy"},{"text":"Billy work on the boss"}],"description":"task to billy"},{"intent":"Tasks","examples":[{"text":"my tasks"},{"text":"What are my tasks?"},{"text":"what am I suppose to do?"},{"text":"what to do?"},{"text":"duties?"},{"text":"whats the task"},{"text":"what need to be done?"},{"text":"tasks"}],"description":"ManagerWantsToKnowHisTasks"},{"intent":"status_on_9_5","examples":[{"text":"today is 5th, what is pending?"},{"text":"today is 9/5, what's left to do?"},{"text":"what's left to do on 9/5"}],"description":"status on 9/5"},{"intent":"Jons_work","examples":[{"text":"what are you up to jon?"},{"text":"What work jon is doing?"},{"text":"What is jon working on?"}],"description":"Current work by jon"},{"intent":"Jons_task","examples":[{"text":"fix the bug Jon"},{"text":"Jon fix the bug"}],"description":"taks given to jon"}],"entities":[{"entity":"sys-date","values":[]},{"entity":"employees","values":[{"type":"synonyms","value":"Jon Johnson","synonyms":["jon","johnson","software developer","developer"]},{"type":"synonyms","value":"Billy","synonyms":["Bill","software intern","intern"]}],"fuzzy_match":true},{"entity":"sys-time","values":[]}],"language":"en","metadata":{"api_version":{"major_version":"v1","minor_version":"2018-07-10"}},"description":"YouKnowIt'sForTheDemoThursday. SellItToTheInstructor'sGranny.","dialog_nodes":[{"type":"standard","title":"My_Team","output":{"generic":[{"title":"You have 2 employees:","options":[{"label":"Jon Johnson","value":{"input":{"text":"Software Developer"}}},{"label":"Billy","value":{"input":{"text":"Software Intern"}}}],"response_type":"option"}]},"metadata":{},"conditions":"#MyEmployees","dialog_node":"node_3_1536186176773","previous_sibling":"node_2_1536185416234"},{"type":"standard","title":"status_on_9/5","output":{"generic":[{"values":[{"text":"The following tasks currently need to be done before release:         2. Code final boss attacks             Estimated time: 1 day             Man-hours spent: 1 day             Current Workers: Jon Johnson         3. Add battle royale mode             Estimated time: 3 days             Current Workers: None "}],"response_type":"text","selection_policy":"sequential"}]},"metadata":{},"conditions":"#status_on_9_5","dialog_node":"node_6_1536189860024","previous_sibling":"node_5_1536189290907"},{"type":"standard","title":"My_Tasks","output":{"generic":[{"title":"The following tasks currently need to be done before release and are in order:","options":[{"label":"Fix bug where player will fly upwards into space.","value":{"input":{"text":""}}},{"label":"Code final boss attacks.","value":{"input":{"text":""}}},{"label":"Add battle royale mode.","value":{"input":{"text":""}}}],"response_type":"option"}]},"metadata":{},"conditions":"#Tasks","dialog_node":"node_2_1536185416234","previous_sibling":"node_1_1536185073168"},{"type":"standard","title":"billy_work","output":{"generic":[{"values":[{"text":"Billy did not show up today"}],"response_type":"text","selection_policy":"sequential"}]},"metadata":{},"conditions":"#Billys_work","dialog_node":"node_2_1536188525667","previous_sibling":"node_1_1536188249420"},{"type":"standard","title":"status_on_9/4","output":{"generic":[{"values":[{"text":"The following tasks currently need to be done before release.  2. Code final boss attacks : Estimated time: 1 day,   Man-hours spent: 1 day,  Current Workers: Jon Johnson 3. Add battle royale mode  Estimated time: 3 days   Current Workers: None    Employee Status:          1. Jon Johnson   \tJob Title: Software Developer  \t Current Task: 2. Code final boss attacks   \tSatisfaction: Content         2. Billy   \tJob Title: Software Intern   \tCurrent Task: None  \t Satisfaction: Disgruntled        Overall Performance Grade: 80/100         Productivity: 90/100         Employee Relations: 70/100 "}],"response_type":"text","selection_policy":"sequential"}]},"metadata":{},"conditions":"#Daily_report_9_4","dialog_node":"node_5_1536189290907","previous_sibling":"node_4_1536188874626"},{"type":"standard","title":"jons_task","output":{"generic":[{"values":[{"text":"Aye aye captain"}],"response_type":"text","selection_policy":"sequential"}]},"metadata":{},"conditions":"#Jons_task","dialog_node":"node_4_1536188874626","previous_sibling":"node_3_1536188796246"},{"type":"standard","title":"Billys_task","output":{"generic":[{"values":[{"text":"Yes sir, I really wanted to do the battle royale, but your word is law"}],"response_type":"text","selection_policy":"sequential"}]},"metadata":{},"conditions":"#Task_to_billy","dialog_node":"node_3_1536188796246","previous_sibling":"node_2_1536188525667"},{"type":"standard","title":"Jons_work_status","output":{"generic":[{"values":[{"text":" Current Task: 2. Code final boss attacks"}],"response_type":"text","selection_policy":"sequential"}]},"metadata":{},"conditions":"#Jons_work","dialog_node":"node_1_1536188249420","previous_sibling":"node_3_1536186176773"},{"type":"standard","title":"Anything else","output":{"generic":[{"values":[{"text":"I didn't understand. You can try rephrasing."},{"text":"Can you reword your statement? I'm not understanding."},{"text":"I didn't get your meaning."}],"response_type":"text","selection_policy":"sequential"}]},"metadata":{},"conditions":"anything_else","dialog_node":"Anything else","previous_sibling":"node_6_1536189860024"},{"type":"standard","title":"Current_Project(s)","output":{"generic":[{"values":[{"text":"You are the manager of the software team for Manager Simulator 4."}],"response_type":"text","selection_policy":"sequential"},{"values":[{"text":"The deadline is in 5 days, 9/9."}],"response_type":"text","selection_policy":"sequential"}]},"metadata":{},"conditions":"#Project","dialog_node":"node_1_1536185073168","previous_sibling":"Welcome"},{"type":"standard","title":"Welcome","output":{"generic":[{"values":[{"text":"Welcome to the Manager Training Simulator v0.63."}],"response_type":"text","selection_policy":"multiline"},{"time":1,"typing":true,"response_type":"pause"},{"values":[{"text":"You are the manager of the new game Manager Simulator 4's software team, now manage it."}],"response_type":"text","selection_policy":"multiline"}]},"metadata":{},"conditions":"welcome","dialog_node":"Welcome"}],"workspace_id":"78d3c1ec-3249-4d36-af63-d87eda739841","counterexamples":[],"system_settings":{"tooling":{"store_generic_responses":true},"disambiguation":{"prompt":"Did you mean:","none_of_the_above_prompt":"None of the above"},"human_agent_assist":{"prompt":"Did you mean:"}},"learning_opt_out":false}